[
  { "title": "Two Sum", "difficulty": "Easy", "category": "Array" },
  { "title": "Reverse String", "difficulty": "Easy", "category": "String" },
  { "title": "Valid Parentheses", "difficulty": "Easy", "category": "Stack" },
  { "title": "Merge Two Sorted Lists", "difficulty": "Easy", "category": "Linked List" },
  { "title": "Best Time to Buy and Sell Stock", "difficulty": "Easy", "category": "Array" },
  { "title": "Add Two Numbers", "difficulty": "Medium", "category": "Linked List" },
  { "title": "Longest Substring Without Repeating Characters", "difficulty": "Medium", "category": "String" },
  { "title": "Median of Two Sorted Arrays", "difficulty": "Hard", "category": "Array" },
  { "title": "Regular Expression Matching", "difficulty": "Hard", "category": "String" },
  { "title": "Merge k Sorted Lists", "difficulty": "Hard", "category": "Linked List" },
  { "title": "Contains Duplicate", "difficulty": "Easy", "category": "Array" },
  { "title": "Valid Anagram", "difficulty": "Easy", "category": "String" },
  { "title": "Group Anagrams", "difficulty": "Medium", "category": "String" },
  { "title": "Top K Frequent Elements", "difficulty": "Medium", "category": "Hash Map" },
  { "title": "LRU Cache", "difficulty": "Medium", "category": "Design" },
  { "title": "Word Ladder", "difficulty": "Hard", "category": "Graph" },
  { "title": "Serialize and Deserialize Binary Tree", "difficulty": "Hard", "category": "Tree" },
  { "title": "Binary Tree Level Order Traversal", "difficulty": "Medium", "category": "Tree" },
  { "title": "Lowest Common Ancestor of a Binary Search Tree", "difficulty": "Easy", "category": "Tree" },
  { "title": "Balanced Binary Tree", "difficulty": "Easy", "category": "Tree" },
  { "title": "Maximum Subarray", "difficulty": "Medium", "category": "Array" },
  { "title": "Jump Game", "difficulty": "Medium", "category": "Greedy" },
  { "title": "Coin Change", "difficulty": "Medium", "category": "Dynamic Programming" },
  { "title": "House Robber", "difficulty": "Medium", "category": "Dynamic Programming" },
  { "title": "Decode Ways", "difficulty": "Medium", "category": "Dynamic Programming" },
  { "title": "Number of Islands", "difficulty": "Medium", "category": "Graph" },
  { "title": "Surrounded Regions", "difficulty": "Medium", "category": "Graph" },
  { "title": "Course Schedule", "difficulty": "Medium", "category": "Graph" },
  { "title": "Alien Dictionary", "difficulty": "Hard", "category": "Graph" },
  { "title": "Minimum Window Substring", "difficulty": "Hard", "category": "String" },
  { "title": "Longest Palindromic Substring", "difficulty": "Medium", "category": "String" },
  { "title": "Zigzag Conversion", "difficulty": "Medium", "category": "String" },
  { "title": "String to Integer (atoi)", "difficulty": "Medium", "category": "String" },
  { "title": "Palindrome Number", "difficulty": "Easy", "category": "Math" },
  { "title": "Roman to Integer", "difficulty": "Easy", "category": "String" },
  { "title": "Integer to Roman", "difficulty": "Medium", "category": "String" },
  { "title": "3Sum", "difficulty": "Medium", "category": "Array" },
  { "title": "3Sum Closest", "difficulty": "Medium", "category": "Array" },
  { "title": "Remove Nth Node From End of List", "difficulty": "Medium", "category": "Linked List" },
  { "title": "Generate Parentheses", "difficulty": "Medium", "category": "Backtracking" },
  { "title": "Swap Nodes in Pairs", "difficulty": "Medium", "category": "Linked List" },
  { "title": "Reverse Nodes in k-Group", "difficulty": "Hard", "category": "Linked List" },
  { "title": "Divide Two Integers", "difficulty": "Medium", "category": "Math" },
  { "title": "Implement strStr()", "difficulty": "Easy", "category": "String" },
  { "title": "Next Permutation", "difficulty": "Medium", "category": "Array" },
  { "title": "Search in Rotated Sorted Array", "difficulty": "Medium", "category": "Array" },
  { "title": "Search in Rotated Sorted Array II", "difficulty": "Hard", "category": "Array" },
  { "title": "Find First and Last Position of Element in Sorted Array", "difficulty": "Medium", "category": "Array" },
  { "title": "Search Insert Position", "difficulty": "Easy", "category": "Array" },
  { "title": "Longest Valid Parentheses", "difficulty": "Hard", "category": "Dynamic Programming" }
]